zealand/__init__.py
zealand/listener.py
zealand/version.py
kiwitcms_robotframework_plugin-12.7.dist-info/LICENSE
kiwitcms_robotframework_plugin-12.7.dist-info/METADATA
kiwitcms_robotframework_plugin-12.7.dist-info/WHEEL
kiwitcms_robotframework_plugin-12.7.dist-info/top_level.txt
kiwitcms_robotframework_plugin-12.7.dist-info/RECORD
