Metadata-Version: 2.1
Name: kiwitcms-robotframework-plugin
Version: 12.7
Summary: robotframework integration with kiwi TCMS
Home-page: https://github.com/kiwitcms/robotframework-plugin
Author: Aniello Barletta
Author-email: aniellob@gmail.com
Maintainer: Kiwi TCMS
Maintainer-email: info@kiwitcms.org
License: GPLv3+
Classifier: Development Status :: 5 - Production/Stable
Classifier: Environment :: Console
Classifier: Intended Audience :: Developers
Classifier: Intended Audience :: System Administrators
Classifier: License :: OSI Approved :: GNU General Public License v3 or later (GPLv3+)
Classifier: Operating System :: POSIX
Classifier: Programming Language :: Python
Classifier: Programming Language :: Python :: 3.8
Classifier: Programming Language :: Python :: 3.11
Classifier: Topic :: Software Development
Classifier: Topic :: Software Development :: Libraries :: Python Modules
Classifier: Topic :: Software Development :: Quality Assurance
Classifier: Topic :: Software Development :: Testing
License-File: LICENSE
Requires-Dist: robotframework (==6.1.1)
Requires-Dist: tcms-api (>=12.7)
